zaojun/__init__.py
zaojun-0.9.7.dist-info/WHEEL
zaojun-0.9.7.dist-info/entry_points.txt
zaojun-0.9.7.dist-info/METADATA
zaojun-0.9.7.dist-info/RECORD
