Metadata-Version: 2.3
Name: zaojun
Version: 0.9.7
Summary: Checks project dependencies for newer versions.
Author: Marvin8
Author-email: Marvin8 <marvin8@tuta.io>
License: AGPL-3.0-or-later
Classifier: Development Status :: 5 - Production/Stable
Classifier: Environment :: Console
Classifier: Intended Audience :: Developers
Classifier: Operating System :: OS Independent
Classifier: Programming Language :: Python
Classifier: Programming Language :: Python :: 3.11
Classifier: Programming Language :: Python :: 3.12
Classifier: Programming Language :: Python :: 3.13
Classifier: Programming Language :: Python :: 3.14
Classifier: Topic :: Utilities
Requires-Dist: h11~=0.16.0
Requires-Dist: h2~=4.3.0
Requires-Dist: httpx[http2,zstd]~=0.28.1
Requires-Dist: packaging~=26.0
Requires-Dist: typer~=0.21.1
Requires-Python: >=3.11, <3.15
Project-URL: Changelog, https://codeberg.org/marvin8/zaojun/src/branch/main/CHANGELOG.md
Project-URL: Issues, https://codeberg.org/marvin8/zaojun/issues
Project-URL: Source, https://codeberg.org/marvin8/zaojun
